facebook_page_scraper/__init__.py
facebook_page_scraper/page_info.py
facebook_page_scraper/page_post_info.py
facebook_page_scraper/request_handler.py
fb_page_data_scraper-0.0.1.dist-info/LICENSE
fb_page_data_scraper-0.0.1.dist-info/METADATA
fb_page_data_scraper-0.0.1.dist-info/WHEEL
fb_page_data_scraper-0.0.1.dist-info/top_level.txt
fb_page_data_scraper-0.0.1.dist-info/RECORD
