Metadata-Version: 2.1
Name: fb-page-data-scraper
Version: 0.0.1
Summary: Facebook page scraper is a python package that helps you scrape data from facebook page.
Home-page: https://github.com/SSujitX/facebook-page-scraper
Author: Sujit Biswas
Author-email: ssujitxx@gmail.com
License: MIT
Project-URL: Bug Tracker, https://github.com/SSujitX/facebook-page-scraper/issues
Project-URL: Documentation, https://github.com/SSujitX/facebook-page-scraper#readme
Project-URL: Source Code, https://github.com/SSujitX/facebook-page-scraper
Keywords: facebook page scraper,scrape facebook page info,facebook data scraper,facebook page info extractor,python facebook scraper
Classifier: Programming Language :: Python :: 3
Classifier: License :: OSI Approved :: MIT License
Classifier: Operating System :: OS Independent
Requires-Python: >=3.9
License-File: LICENSE
Requires-Dist: curl-cffi
Requires-Dist: selectolax
